{
    "market": {
        "0": {
            "id": 0,
            "code": "C94",
            "name": "WinMart+ 120 Lê Duẩn (Ga Hà Nội)",
            "location": {
                "lat": 21.0242529,
                "long": 105.841029
            },
            "demand_list": {
                "1": {
                    "item_id": 1,
                    "demand": 207
                }
            },
            "seller": "C116",
            "start_time": 27000,
            "end_time": 73800
        },
        "1": {
            "id": 1,
            "code": "C177",
            "name": "WinMart+ Lĩnh Nam",
            "location": {
                "lat": 20.9825137,
                "long": 105.8816702
            },
            "demand_list": {
                "1": {
                    "item_id": 1,
                    "demand": 451
                }
            },
            "seller": "C423",
            "start_time": 28800,
            "end_time": 79200
        },
        "2": {
            "id": 2,
            "code": "C144",
            "name": "WinMart+ N07B2 Dịch Vọng",
            "location": {
                "lat": 21.0377821,
                "long": 105.7969492
            },
            "demand_list": {
                "1": {
                    "item_id": 1,
                    "demand": 387
                }
            },
            "seller": "C461",
            "start_time": 28800,
            "end_time": 79200
        },
        "3": {
            "id": 3,
            "code": "C281",
            "name": "WinMart+ 84 Bế Văn Đàn - Hà Đông",
            "location": {
                "lat": 20.9688503,
                "long": 105.7721037
            },
            "demand_list": {
                "1": {
                    "item_id": 1,
                    "demand": 29
                }
            },
            "seller": "C116",
            "start_time": 27000,
            "end_time": 79200
        },
        "4": {
            "id": 4,
            "code": "C146",
            "name": "WinMart+ 90 Dương Quảng Hàm",
            "location": {
                "lat": 21.0352695,
                "long": 105.8003763
            },
            "demand_list": {
                "1": {
                    "item_id": 1,
                    "demand": 201
                }
            },
            "seller": "C221",
            "start_time": 28800,
            "end_time": 79200
        },
        "5": {
            "id": 5,
            "code": "C401",
            "name": "Vua nệm - 142 Nguyễn Chánh",
            "location": {
                "lat": 21.0188271,
                "long": 105.7870322
            },
            "demand_list": {
                "1": {
                    "item_id": 1,
                    "demand": 467
                }
            },
            "seller": "C143",
            "start_time": 30600,
            "end_time": 75600
        },
        "6": {
            "id": 6,
            "code": "C50",
            "name": "WinMart+ 38 Linh Lang",
            "location": {
                "lat": 21.0360361,
                "long": 105.8104245
            },
            "demand_list": {
                "1": {
                    "item_id": 1,
                    "demand": 335
                }
            },
            "seller": "C423",
            "start_time": 27900,
            "end_time": 74700
        },
        "7": {
            "id": 7,
            "code": "C87",
            "name": "Siêu thị WinMart Thái Nguyên",
            "location": {
                "lat": 21.5909003,
                "long": 105.8259454
            },
            "demand_list": {
                "1": {
                    "item_id": 1,
                    "demand": 303
                }
            },
            "seller": "C461",
            "start_time": 27000,
            "end_time": 73800
        },
        "8": {
            "id": 8,
            "code": "C336",
            "name": "Circle K - 79 P. Hà Trung",
            "location": {
                "lat": 21.0299461,
                "long": 105.8450038
            },
            "demand_list": {
                "1": {
                    "item_id": 1,
                    "demand": 321
                }
            },
            "seller": "C22",
            "start_time": 25200,
            "end_time": 75600
        },
        "9": {
            "id": 9,
            "code": "C297",
            "name": "Circle K 232 Lạc Trung",
            "location": {
                "lat": 21.003125,
                "long": 105.8668833
            },
            "demand_list": {
                "1": {
                    "item_id": 1,
                    "demand": 88
                }
            },
            "seller": "C259",
            "start_time": 25200,
            "end_time": 75600
        },
        "10": {
            "id": 10,
            "code": "C275",
            "name": "WinMart+ 31 Xuân Đỉnh",
            "location": {
                "lat": 21.0699492,
                "long": 105.8016547
            },
            "demand_list": {
                "1": {
                    "item_id": 1,
                    "demand": 410
                }
            },
            "seller": "C221",
            "start_time": 27000,
            "end_time": 79200
        },
        "11": {
            "id": 11,
            "code": "C450",
            "name": "TH true mart Đại Mỗ Hà Nội",
            "location": {
                "lat": 20.9954527,
                "long": 105.7540631
            },
            "demand_list": {
                "1": {
                    "item_id": 1,
                    "demand": 416
                }
            },
            "seller": "C423",
            "start_time": 28800,
            "end_time": 79200
        },
        "12": {
            "id": 12,
            "code": "C447",
            "name": "TH true mart Minh Khai Hà Nội",
            "location": {
                "lat": 20.996619,
                "long": 105.863613
            },
            "demand_list": {
                "1": {
                    "item_id": 1,
                    "demand": 212
                }
            },
            "seller": "C5",
            "start_time": 28800,
            "end_time": 79200
        },
        "13": {
            "id": 13,
            "code": "C51",
            "name": "WinMart+ 29A Nguyễn Công Hoan",
            "location": {
                "lat": 21.0272409,
                "long": 105.8145485
            },
            "demand_list": {
                "1": {
                    "item_id": 1,
                    "demand": 417
                }
            },
            "seller": "C5",
            "start_time": 27900,
            "end_time": 74700
        },
        "14": {
            "id": 14,
            "code": "C246",
            "name": "WinMart+ 601 Kim Ngưu",
            "location": {
                "lat": 20.9981624,
                "long": 105.8623923
            },
            "demand_list": {
                "1": {
                    "item_id": 1,
                    "demand": 378
                }
            },
            "seller": "C221",
            "start_time": 27000,
            "end_time": 79200
        },
        "15": {
            "id": 15,
            "code": "C247",
            "name": "WinMart+ 194 Minh Khai",
            "location": {
                "lat": 20.9952768,
                "long": 105.854344
            },
            "demand_list": {
                "1": {
                    "item_id": 1,
                    "demand": 466
                }
            },
            "seller": "C143",
            "start_time": 27000,
            "end_time": 79200
        },
        "16": {
            "id": 16,
            "code": "C362",
            "name": "Điện máy xanh - 55 P. Nguyễn Hoàng",
            "location": {
                "lat": 21.0320869,
                "long": 105.773378
            },
            "demand_list": {
                "1": {
                    "item_id": 1,
                    "demand": 464
                }
            },
            "seller": "C22",
            "start_time": 28800,
            "end_time": 79200
        },
        "17": {
            "id": 17,
            "code": "C421",
            "name": "Siêu thị Điện máy XANH - Khu Cống Đặng",
            "location": {
                "lat": 21.0236074,
                "long": 105.6115294
            },
            "demand_list": {
                "1": {
                    "item_id": 1,
                    "demand": 333
                }
            },
            "seller": "C53",
            "start_time": 28800,
            "end_time": 79200
        },
        "18": {
            "id": 18,
            "code": "C157",
            "name": "WinMart+ 22 Bùi Xương Trạch",
            "location": {
                "lat": 20.9916094,
                "long": 105.8172299
            },
            "demand_list": {
                "1": {
                    "item_id": 1,
                    "demand": 70
                }
            },
            "seller": "C461",
            "start_time": 28800,
            "end_time": 79200
        },
        "19": {
            "id": 19,
            "code": "C435",
            "name": "Nội Thất Tân Cổ Điển",
            "location": {
                "lat": 21.0288501,
                "long": 105.8307387
            },
            "demand_list": {
                "1": {
                    "item_id": 1,
                    "demand": 62
                }
            },
            "seller": "C423",
            "start_time": 28800,
            "end_time": 79200
        },
        "20": {
            "id": 20,
            "code": "C182",
            "name": "WinMart+ 182 Đại Từ",
            "location": {
                "lat": 20.9711174,
                "long": 105.8335134
            },
            "demand_list": {
                "1": {
                    "item_id": 1,
                    "demand": 377
                }
            },
            "seller": "C221",
            "start_time": 28800,
            "end_time": 79200
        },
        "21": {
            "id": 21,
            "code": "C232",
            "name": "WinMart+ 167 Trần Đại Nghĩa",
            "location": {
                "lat": 21.0005319,
                "long": 105.8454571
            },
            "demand_list": {
                "1": {
                    "item_id": 1,
                    "demand": 109
                }
            },
            "seller": "C461",
            "start_time": 27000,
            "end_time": 79200
        },
        "22": {
            "id": 22,
            "code": "C150",
            "name": "WinMart+ Ngõ 76 Mai Dịch",
            "location": {
                "lat": 21.0170417,
                "long": 105.7993846
            },
            "demand_list": {
                "1": {
                    "item_id": 1,
                    "demand": 407
                }
            },
            "seller": "C259",
            "start_time": 28800,
            "end_time": 79200
        },
        "23": {
            "id": 23,
            "code": "C62",
            "name": "WinMart Thăng Long",
            "location": {
                "lat": 21.0382547,
                "long": 105.7940821
            },
            "demand_list": {
                "1": {
                    "item_id": 1,
                    "demand": 210
                }
            },
            "seller": "C53",
            "start_time": 27000,
            "end_time": 73800
        },
        "24": {
            "id": 24,
            "code": "C19",
            "name": "WinMart+ Hoàng Văn Thái",
            "location": {
                "lat": 20.9975522,
                "long": 105.8228263
            },
            "demand_list": {
                "1": {
                    "item_id": 1,
                    "demand": 150
                }
            },
            "seller": "C22",
            "start_time": 28800,
            "end_time": 75600
        },
        "25": {
            "id": 25,
            "code": "C175",
            "name": "WinMart+ 261 Tân Mai",
            "location": {
                "lat": 20.9836299,
                "long": 105.8550986
            },
            "demand_list": {
                "1": {
                    "item_id": 1,
                    "demand": 115
                }
            },
            "seller": "C116",
            "start_time": 28800,
            "end_time": 79200
        },
        "26": {
            "id": 26,
            "code": "C160",
            "name": "WinMart+ 47 Khương Đình",
            "location": {
                "lat": 20.9967425,
                "long": 105.8136954
            },
            "demand_list": {
                "1": {
                    "item_id": 1,
                    "demand": 204
                }
            },
            "seller": "C423",
            "start_time": 28800,
            "end_time": 79200
        },
        "27": {
            "id": 27,
            "code": "C60",
            "name": "WinMart+ 17B Đoàn Thị Điểm",
            "location": {
                "lat": 21.0260252,
                "long": 105.8326648
            },
            "demand_list": {
                "1": {
                    "item_id": 1,
                    "demand": 86
                }
            },
            "seller": "C22",
            "start_time": 27900,
            "end_time": 74700
        },
        "28": {
            "id": 28,
            "code": "C101",
            "name": "WinMart+ Khu đô thị mới, Gia Lâm",
            "location": {
                "lat": 21.0287612,
                "long": 105.9611748
            },
            "demand_list": {
                "1": {
                    "item_id": 1,
                    "demand": 165
                }
            },
            "seller": "C53",
            "start_time": 27000,
            "end_time": 73800
        },
        "29": {
            "id": 29,
            "code": "C436",
            "name": "Cửa Hàng Nội Thất Đẹp",
            "location": {
                "lat": 21.0217072,
                "long": 105.8264039
            },
            "demand_list": {
                "1": {
                    "item_id": 1,
                    "demand": 195
                }
            },
            "seller": "C116",
            "start_time": 28800,
            "end_time": 79200
        },
        "30": {
            "id": 30,
            "code": "C287",
            "name": "WinMart+ B15 Bồ Hỏa - Hà Đông",
            "location": {
                "lat": 20.966173,
                "long": 105.7755831
            },
            "demand_list": {
                "1": {
                    "item_id": 1,
                    "demand": 237
                }
            },
            "seller": "C273",
            "start_time": 27000,
            "end_time": 79200
        },
        "31": {
            "id": 31,
            "code": "C225",
            "name": "WinMart+ 348 Lạc Trung",
            "location": {
                "lat": 21.003158,
                "long": 105.868858
            },
            "demand_list": {
                "1": {
                    "item_id": 1,
                    "demand": 272
                }
            },
            "seller": "C259",
            "start_time": 27000,
            "end_time": 79200
        },
        "32": {
            "id": 32,
            "code": "C93",
            "name": "WinMart+ 23 Gia Ngư",
            "location": {
                "lat": 21.0331231,
                "long": 105.8527578
            },
            "demand_list": {
                "1": {
                    "item_id": 1,
                    "demand": 189
                }
            },
            "seller": "C53",
            "start_time": 27000,
            "end_time": 73800
        },
        "33": {
            "id": 33,
            "code": "C317",
            "name": "Circle K - 46 Lê Trọng Tấn",
            "location": {
                "lat": 20.9997704,
                "long": 105.8277226
            },
            "demand_list": {
                "1": {
                    "item_id": 1,
                    "demand": 106
                }
            },
            "seller": "C259",
            "start_time": 25200,
            "end_time": 75600
        },
        "34": {
            "id": 34,
            "code": "C97",
            "name": "WinMart+ 20 Ngõ Huyện",
            "location": {
                "lat": 21.0298374,
                "long": 105.848524
            },
            "demand_list": {
                "1": {
                    "item_id": 1,
                    "demand": 357
                }
            },
            "seller": "C423",
            "start_time": 27000,
            "end_time": 73800
        },
        "35": {
            "id": 35,
            "code": "C100",
            "name": "WinMart+ 4A Phố Hàng Chiếu",
            "location": {
                "lat": 21.037291,
                "long": 105.852077
            },
            "demand_list": {
                "1": {
                    "item_id": 1,
                    "demand": 168
                }
            },
            "seller": "C5",
            "start_time": 27000,
            "end_time": 73800
        },
        "36": {
            "id": 36,
            "code": "C67",
            "name": "WinMart Vũ Trọng Phụng",
            "location": {
                "lat": 20.999531,
                "long": 105.8074389
            },
            "demand_list": {
                "1": {
                    "item_id": 1,
                    "demand": 14
                }
            },
            "seller": "C22",
            "start_time": 27000,
            "end_time": 73800
        },
        "37": {
            "id": 37,
            "code": "C284",
            "name": "WinMart+ Lô 11 Liền Kề 19 Mậu Lương",
            "location": {
                "lat": 20.9556769,
                "long": 105.7929888
            },
            "demand_list": {
                "1": {
                    "item_id": 1,
                    "demand": 476
                }
            },
            "seller": "C273",
            "start_time": 27000,
            "end_time": 79200
        },
        "38": {
            "id": 38,
            "code": "C57",
            "name": "WinMart+ 1132 Đường Láng",
            "location": {
                "lat": 21.0252216,
                "long": 105.7986565
            },
            "demand_list": {},
            "seller": "C53",
            "start_time": 27900,
            "end_time": 74700
        },
        "39": {
            "id": 39,
            "code": "C251",
            "name": "WinMart+ 48 Lê Thanh Nghị",
            "location": {
                "lat": 21.0034188,
                "long": 105.8491825
            },
            "demand_list": {
                "1": {
                    "item_id": 1,
                    "demand": 360
                }
            },
            "seller": "C5",
            "start_time": 27000,
            "end_time": 79200
        },
        "40": {
            "id": 40,
            "code": "C315",
            "name": "Circle K - Lò Đúc",
            "location": {
                "lat": 21.0134239,
                "long": 105.8579048
            },
            "demand_list": {
                "1": {
                    "item_id": 1,
                    "demand": 98
                }
            },
            "seller": "C143",
            "start_time": 25200,
            "end_time": 75600
        },
        "41": {
            "id": 41,
            "code": "C449",
            "name": "TH true mart Vạn Phúc Hà Nội",
            "location": {
                "lat": 20.9800059,
                "long": 105.7721462
            },
            "demand_list": {
                "1": {
                    "item_id": 1,
                    "demand": 15
                }
            },
            "seller": "C259",
            "start_time": 28800,
            "end_time": 79200
        },
        "42": {
            "id": 42,
            "code": "C325",
            "name": "Circle K - 62 Trần Hưng Đạo",
            "location": {
                "lat": 21.0221733,
                "long": 105.8489029
            },
            "demand_list": {
                "1": {
                    "item_id": 1,
                    "demand": 376
                }
            },
            "seller": "C22",
            "start_time": 25200,
            "end_time": 75600
        },
        "43": {
            "id": 43,
            "code": "C168",
            "name": "VinMart+  Nguyễn Đức Cảnh",
            "location": {
                "lat": 20.9879025,
                "long": 105.8517093
            },
            "demand_list": {
                "1": {
                    "item_id": 1,
                    "demand": 140
                }
            },
            "seller": "C116",
            "start_time": 28800,
            "end_time": 79200
        },
        "44": {
            "id": 44,
            "code": "C18",
            "name": "WinMart Văn Quá",
            "location": {
                "lat": 20.9703841,
                "long": 105.7868365
            },
            "demand_list": {
                "1": {
                    "item_id": 1,
                    "demand": 131
                }
            },
            "seller": "C423",
            "start_time": 28800,
            "end_time": 75600
        },
        "45": {
            "id": 45,
            "code": "C186",
            "name": "WinMart+ 207 Định Công Thượng",
            "location": {
                "lat": 20.9846035,
                "long": 105.8232334
            },
            "demand_list": {
                "1": {
                    "item_id": 1,
                    "demand": 438
                }
            },
            "seller": "C461",
            "start_time": 28800,
            "end_time": 79200
        },
        "46": {
            "id": 46,
            "code": "C25",
            "name": "VinMart+ 266 Đào Cam Mộc",
            "location": {
                "lat": 21.1412991,
                "long": 105.8684964
            },
            "demand_list": {
                "1": {
                    "item_id": 1,
                    "demand": 90
                }
            },
            "seller": "C423",
            "start_time": 28800,
            "end_time": 75600
        },
        "47": {
            "id": 47,
            "code": "C169",
            "name": "WinMart+ Lô 8- 3A Kcn Hoàng Mai",
            "location": {
                "lat": 20.9863393,
                "long": 105.8635604
            },
            "demand_list": {
                "1": {
                    "item_id": 1,
                    "demand": 427
                }
            },
            "seller": "C53",
            "start_time": 28800,
            "end_time": 79200
        },
        "48": {
            "id": 48,
            "code": "C268",
            "name": "WinMart+ 29 Ngõ 126 Xuân Đỉnh",
            "location": {
                "lat": 21.072132,
                "long": 105.7985533
            },
            "demand_list": {
                "1": {
                    "item_id": 1,
                    "demand": 228
                }
            },
            "seller": "C461",
            "start_time": 27000,
            "end_time": 79200
        },
        "49": {
            "id": 49,
            "code": "C98",
            "name": "WinMart+ Số 8 Lê Văn Linh",
            "location": {
                "lat": 21.037465,
                "long": 105.845865
            },
            "demand_list": {
                "1": {
                    "item_id": 1,
                    "demand": 253
                }
            },
            "seller": "C116",
            "start_time": 27000,
            "end_time": 73800
        },
        "50": {
            "id": 50,
            "code": "C121",
            "name": "WinMart+ Packexim",
            "location": {
                "lat": 21.0869945,
                "long": 105.8146509
            },
            "demand_list": {
                "1": {
                    "item_id": 1,
                    "demand": 488
                }
            },
            "seller": "C53",
            "start_time": 27000,
            "end_time": 73800
        },
        "51": {
            "id": 51,
            "code": "C45",
            "name": "WinMart+ 575 La Thành",
            "location": {
                "lat": 21.0237555,
                "long": 105.8171405
            },
            "demand_list": {
                "1": {
                    "item_id": 1,
                    "demand": 424
                }
            },
            "seller": "C143",
            "start_time": 27900,
            "end_time": 74700
        },
        "52": {
            "id": 52,
            "code": "C187",
            "name": "WinMart+ 589 Trương Định",
            "location": {
                "lat": 20.9812164,
                "long": 105.845372
            },
            "demand_list": {
                "1": {
                    "item_id": 1,
                    "demand": 375
                }
            },
            "seller": "C116",
            "start_time": 28800,
            "end_time": 79200
        },
        "53": {
            "id": 53,
            "code": "C159",
            "name": "WinMart+ 77 Chính Kinh",
            "location": {
                "lat": 20.998957,
                "long": 105.8119449
            },
            "demand_list": {
                "1": {
                    "item_id": 1,
                    "demand": 320
                }
            },
            "seller": "C5",
            "start_time": 28800,
            "end_time": 79200
        },
        "54": {
            "id": 54,
            "code": "C30",
            "name": "WinMart+ 387 Thụy Khuê",
            "location": {
                "lat": 21.0458559,
                "long": 105.8132006
            },
            "demand_list": {
                "1": {
                    "item_id": 1,
                    "demand": 138
                }
            },
            "seller": "C221",
            "start_time": 28800,
            "end_time": 75600
        },
        "55": {
            "id": 55,
            "code": "C11",
            "name": "VinMart Nguyễn Văn Cừ II",
            "location": {
                "lat": 21.0420983,
                "long": 105.8699483
            },
            "demand_list": {
                "1": {
                    "item_id": 1,
                    "demand": 167
                }
            },
            "seller": "C5",
            "start_time": 28800,
            "end_time": 75600
        },
        "56": {
            "id": 56,
            "code": "C129",
            "name": "WinMart+ 19 Lương Đình Của",
            "location": {
                "lat": 21.0062934,
                "long": 105.8355421
            },
            "demand_list": {
                "1": {
                    "item_id": 1,
                    "demand": 25
                }
            },
            "seller": "C423",
            "start_time": 28800,
            "end_time": 79200
        },
        "57": {
            "id": 57,
            "code": "C29",
            "name": "WinMart+ - 60 Tứ Hiệp, Thanh Trì",
            "location": {
                "lat": 20.9486349,
                "long": 105.8455084
            },
            "demand_list": {
                "1": {
                    "item_id": 1,
                    "demand": 30
                }
            },
            "seller": "C423",
            "start_time": 28800,
            "end_time": 75600
        },
        "58": {
            "id": 58,
            "code": "C467",
            "name": "TH true mart Sài Đồng Hà Nội",
            "location": {
                "lat": 21.0351249,
                "long": 105.9104669
            },
            "demand_list": {
                "1": {
                    "item_id": 1,
                    "demand": 262
                }
            },
            "seller": "C143",
            "start_time": 28800,
            "end_time": 79200
        },
        "59": {
            "id": 59,
            "code": "C332",
            "name": "Circle K - 1 Tô Vĩnh Diện",
            "location": {
                "lat": 21.0003557,
                "long": 105.8213606
            },
            "demand_list": {
                "1": {
                    "item_id": 1,
                    "demand": 17
                }
            },
            "seller": "C461",
            "start_time": 25200,
            "end_time": 75600
        },
        "60": {
            "id": 60,
            "code": "C409",
            "name": "Vua nệm -  322 Đ. Nguyễn Trãi",
            "location": {
                "lat": 20.9961652,
                "long": 105.8096789
            },
            "demand_list": {
                "1": {
                    "item_id": 1,
                    "demand": 90
                }
            },
            "seller": "C22",
            "start_time": 30600,
            "end_time": 75600
        },
        "61": {
            "id": 61,
            "code": "C105",
            "name": "WinMart+ 47 QL 2 Phủ Lỗ, Sóc Sơn",
            "location": {
                "lat": 21.4036171,
                "long": 105.3155767
            },
            "demand_list": {
                "1": {
                    "item_id": 1,
                    "demand": 304
                }
            },
            "seller": "C273",
            "start_time": 27000,
            "end_time": 73800
        },
        "62": {
            "id": 62,
            "code": "C219",
            "name": "WinMart+ 27 Ngô Thì Nhậm",
            "location": {
                "lat": 21.0067485,
                "long": 105.8503135
            },
            "demand_list": {
                "1": {
                    "item_id": 1,
                    "demand": 417
                }
            },
            "seller": "C461",
            "start_time": 27000,
            "end_time": 79200
        },
        "63": {
            "id": 63,
            "code": "C418",
            "name": "Vua nệm -  Vinsmart, S201-01SH15",
            "location": {
                "lat": 21.0088528,
                "long": 105.7439194
            },
            "demand_list": {
                "1": {
                    "item_id": 1,
                    "demand": 119
                }
            },
            "seller": "C259",
            "start_time": 30600,
            "end_time": 75600
        },
        "64": {
            "id": 64,
            "code": "C23",
            "name": "VinMart+ 3 Hàng Bút",
            "location": {
                "lat": 21.0349538,
                "long": 105.8478689
            },
            "demand_list": {
                "1": {
                    "item_id": 1,
                    "demand": 256
                }
            },
            "seller": "C22",
            "start_time": 28800,
            "end_time": 75600
        },
        "65": {
            "id": 65,
            "code": "C330",
            "name": "Circle K - 2 Phố Hoàng Ngân",
            "location": {
                "lat": 21.0071688,
                "long": 105.8115855
            },
            "demand_list": {
                "1": {
                    "item_id": 1,
                    "demand": 141
                }
            },
            "seller": "C22",
            "start_time": 25200,
            "end_time": 75600
        },
        "66": {
            "id": 66,
            "code": "C181",
            "name": "WinMart+ 12 Đông Thiên",
            "location": {
                "lat": 20.9833673,
                "long": 105.8764531
            },
            "demand_list": {
                "1": {
                    "item_id": 1,
                    "demand": 326
                }
            },
            "seller": "C221",
            "start_time": 28800,
            "end_time": 79200
        },
        "67": {
            "id": 67,
            "code": "C274",
            "name": "WinMart+ 21 Văn Tiến Dũng",
            "location": {
                "lat": 21.048575,
                "long": 105.748747
            },
            "demand_list": {
                "1": {
                    "item_id": 1,
                    "demand": 466
                }
            },
            "seller": "C5",
            "start_time": 27000,
            "end_time": 79200
        },
        "68": {
            "id": 68,
            "code": "C178",
            "name": "WinMart+ 100B/168 Kim Giang",
            "location": {
                "lat": 20.9792367,
                "long": 105.8156714
            },
            "demand_list": {
                "1": {
                    "item_id": 1,
                    "demand": 143
                }
            },
            "seller": "C461",
            "start_time": 28800,
            "end_time": 79200
        },
        "69": {
            "id": 69,
            "code": "C198",
            "name": "WinMart+ 491D Nguyễn Văn Cừ",
            "location": {
                "lat": 21.048673,
                "long": 105.8811986
            },
            "demand_list": {
                "1": {
                    "item_id": 1,
                    "demand": 420
                }
            },
            "seller": "C273",
            "start_time": 28800,
            "end_time": 79200
        },
        "70": {
            "id": 70,
            "code": "C327",
            "name": "Circle K - 91 Khâm Thiên",
            "location": {
                "lat": 21.0189548,
                "long": 105.8375806
            },
            "demand_list": {
                "1": {
                    "item_id": 1,
                    "demand": 131
                }
            },
            "seller": "C22",
            "start_time": 25200,
            "end_time": 75600
        },
        "71": {
            "id": 71,
            "code": "C446",
            "name": "TH true mart Phan Trọng Tuệ Hà Nội",
            "location": {
                "lat": 20.9572832,
                "long": 105.8081957
            },
            "demand_list": {
                "1": {
                    "item_id": 1,
                    "demand": 280
                }
            },
            "seller": "C221",
            "start_time": 28800,
            "end_time": 79200
        },
        "72": {
            "id": 72,
            "code": "C208",
            "name": "WinMart+  Ngõ 22 Phố Phú Viên",
            "location": {
                "lat": 21.0385769,
                "long": 105.8658909
            },
            "demand_list": {
                "1": {
                    "item_id": 1,
                    "demand": 297
                }
            },
            "seller": "C273",
            "start_time": 27000,
            "end_time": 79200
        },
        "73": {
            "id": 73,
            "code": "C130",
            "name": "WinMart+ 166 Kim Hoa",
            "location": {
                "lat": 21.0111212,
                "long": 105.8378198
            },
            "demand_list": {
                "1": {
                    "item_id": 1,
                    "demand": 212
                }
            },
            "seller": "C221",
            "start_time": 28800,
            "end_time": 79200
        },
        "74": {
            "id": 74,
            "code": "C278",
            "name": "WinMart+ 212 Cổ Nhuế",
            "location": {
                "lat": 21.063956,
                "long": 105.779958
            },
            "demand_list": {
                "1": {
                    "item_id": 1,
                    "demand": 7
                }
            },
            "seller": "C461",
            "start_time": 27000,
            "end_time": 79200
        },
        "75": {
            "id": 75,
            "code": "C118",
            "name": "WinMart+ 426 Hoàng Hoa Thám",
            "location": {
                "lat": 21.0418214,
                "long": 105.8352753
            },
            "demand_list": {
                "1": {
                    "item_id": 1,
                    "demand": 139
                }
            },
            "seller": "C53",
            "start_time": 27000,
            "end_time": 73800
        },
        "76": {
            "id": 76,
            "code": "C88",
            "name": "WinMart Việt Trì - Phú Thọ",
            "location": {
                "lat": 21.3124043,
                "long": 105.3947355
            },
            "demand_list": {
                "1": {
                    "item_id": 1,
                    "demand": 338
                }
            },
            "seller": "C5",
            "start_time": 27000,
            "end_time": 73800
        },
        "77": {
            "id": 77,
            "code": "C227",
            "name": "WinMart+ 38 Đê Tô Hoàng",
            "location": {
                "lat": 21.0074001,
                "long": 105.8499148
            },
            "demand_list": {
                "1": {
                    "item_id": 1,
                    "demand": 432
                }
            },
            "seller": "C461",
            "start_time": 27000,
            "end_time": 79200
        },
        "78": {
            "id": 78,
            "code": "C214",
            "name": "WinMart+ 97 Sài Đồng",
            "location": {
                "lat": 21.0359332,
                "long": 105.910896
            },
            "demand_list": {
                "1": {
                    "item_id": 1,
                    "demand": 59
                }
            },
            "seller": "C461",
            "start_time": 27000,
            "end_time": 79200
        },
        "79": {
            "id": 79,
            "code": "C102",
            "name": "WinMart+ Đinh Tiên Hoàng, Sơn Tây",
            "location": {
                "lat": 21.1429395,
                "long": 105.5029561
            },
            "demand_list": {
                "1": {
                    "item_id": 1,
                    "demand": 18
                }
            },
            "seller": "C53",
            "start_time": 27000,
            "end_time": 73800
        },
        "80": {
            "id": 80,
            "code": "C236",
            "name": "WinMart+ 70 Vạn Kiếp",
            "location": {
                "lat": 21.0187737,
                "long": 105.8631417
            },
            "demand_list": {
                "1": {
                    "item_id": 1,
                    "demand": 216
                }
            },
            "seller": "C53",
            "start_time": 27000,
            "end_time": 79200
        },
        "81": {
            "id": 81,
            "code": "C68",
            "name": "WinMart Trường Chinh",
            "location": {
                "lat": 20.9999732,
                "long": 105.8363229
            },
            "demand_list": {
                "1": {
                    "item_id": 1,
                    "demand": 262
                }
            },
            "seller": "C461",
            "start_time": 27000,
            "end_time": 73800
        },
        "82": {
            "id": 82,
            "code": "C422",
            "name": "Siêu thị Điện máy XANH - Thạch Thất 5",
            "location": {
                "lat": 20.9905234,
                "long": 105.5251894
            },
            "demand_list": {
                "1": {
                    "item_id": 1,
                    "demand": 395
                }
            },
            "seller": "C221",
            "start_time": 28800,
            "end_time": 79200
        },
        "83": {
            "id": 83,
            "code": "C349",
            "name": "Circle K - 76 Đồng Xuân",
            "location": {
                "lat": 21.037113,
                "long": 105.849374
            },
            "demand_list": {
                "1": {
                    "item_id": 1,
                    "demand": 12
                }
            },
            "seller": "C143",
            "start_time": 25200,
            "end_time": 75600
        },
        "84": {
            "id": 84,
            "code": "C222",
            "name": "WinMart+ 59 Mai Hắc Đế",
            "location": {
                "lat": 21.0145224,
                "long": 105.8511623
            },
            "demand_list": {
                "1": {
                    "item_id": 1,
                    "demand": 449
                }
            },
            "seller": "C259",
            "start_time": 27000,
            "end_time": 79200
        },
        "85": {
            "id": 85,
            "code": "C147",
            "name": "WinMart+ 90 Dương Quảng Hàm",
            "location": {
                "lat": 21.0234101,
                "long": 105.7943758
            },
            "demand_list": {
                "1": {
                    "item_id": 1,
                    "demand": 342
                }
            },
            "seller": "C22",
            "start_time": 28800,
            "end_time": 79200
        },
        "86": {
            "id": 86,
            "code": "C294",
            "name": "WinMart+ 37 Lê Lợi",
            "location": {
                "lat": 20.9711998,
                "long": 105.7776999
            },
            "demand_list": {
                "1": {
                    "item_id": 1,
                    "demand": 266
                }
            },
            "seller": "C53",
            "start_time": 27000,
            "end_time": 79200
        },
        "87": {
            "id": 87,
            "code": "C378",
            "name": "Siêu thị Điện máy XANH Tân Hội, Đan Phượng",
            "location": {
                "lat": 21.0952106,
                "long": 105.7052936
            },
            "demand_list": {
                "1": {
                    "item_id": 1,
                    "demand": 459
                }
            },
            "seller": "C53",
            "start_time": 28800,
            "end_time": 79200
        },
        "88": {
            "id": 88,
            "code": "C285",
            "name": "WinMart+ Liền Kề Lk1-30 Văn Phú",
            "location": {
                "lat": 20.9590191,
                "long": 105.7624874
            },
            "demand_list": {
                "1": {
                    "item_id": 1,
                    "demand": 270
                }
            },
            "seller": "C461",
            "start_time": 27000,
            "end_time": 79200
        },
        "89": {
            "id": 89,
            "code": "C456",
            "name": "TH true mart Xuân Đỉnh Hà Nội",
            "location": {
                "lat": 21.0713757,
                "long": 105.7968163
            },
            "demand_list": {
                "1": {
                    "item_id": 1,
                    "demand": 289
                }
            },
            "seller": "C53",
            "start_time": 28800,
            "end_time": 79200
        },
        "90": {
            "id": 90,
            "code": "C239",
            "name": "WinMart+ 17 Nguyễn Thượng Hiền",
            "location": {
                "lat": 21.018794,
                "long": 105.8426206
            },
            "demand_list": {
                "1": {
                    "item_id": 1,
                    "demand": 312
                }
            },
            "seller": "C259",
            "start_time": 27000,
            "end_time": 79200
        },
        "91": {
            "id": 91,
            "code": "C291",
            "name": "WinMart+ 556 Quang Trung - Hà Đông",
            "location": {
                "lat": 20.959861,
                "long": 105.761454
            },
            "demand_list": {
                "1": {
                    "item_id": 1,
                    "demand": 307
                }
            },
            "seller": "C22",
            "start_time": 27000,
            "end_time": 79200
        },
        "92": {
            "id": 92,
            "code": "C176",
            "name": "WinMart+ 402 Kim Giang",
            "location": {
                "lat": 20.9743944,
                "long": 105.8246947
            },
            "demand_list": {
                "1": {
                    "item_id": 1,
                    "demand": 161
                }
            },
            "seller": "C116",
            "start_time": 28800,
            "end_time": 79200
        },
        "93": {
            "id": 93,
            "code": "C179",
            "name": "WinMart+ 179 Thịnh Liệt",
            "location": {
                "lat": 20.9740814,
                "long": 105.8412509
            },
            "demand_list": {
                "1": {
                    "item_id": 1,
                    "demand": 197
                }
            },
            "seller": "C143",
            "start_time": 28800,
            "end_time": 79200
        },
        "94": {
            "id": 94,
            "code": "C469",
            "name": "TH true mart Nguyễn Khánh Toàn Hà Nội",
            "location": {
                "lat": 21.0355126,
                "long": 105.8041999
            },
            "demand_list": {
                "1": {
                    "item_id": 1,
                    "demand": 364
                }
            },
            "seller": "C22",
            "start_time": 28800,
            "end_time": 79200
        },
        "95": {
            "id": 95,
            "code": "C145",
            "name": "WinMart+ 17 Trần Quốc Hoàn",
            "location": {
                "lat": 21.0416664,
                "long": 105.7855364
            },
            "demand_list": {
                "1": {
                    "item_id": 1,
                    "demand": 170
                }
            },
            "seller": "C221",
            "start_time": 28800,
            "end_time": 79200
        },
        "96": {
            "id": 96,
            "code": "C91",
            "name": "WinMart+ 53 Cao Lỗ",
            "location": {
                "lat": 21.1407545,
                "long": 105.8482196
            },
            "demand_list": {
                "1": {
                    "item_id": 1,
                    "demand": 36
                }
            },
            "seller": "C22",
            "start_time": 27000,
            "end_time": 73800
        },
        "97": {
            "id": 97,
            "code": "C306",
            "name": "Circle K Imperial",
            "location": {
                "lat": 20.9983503,
                "long": 105.8668477
            },
            "demand_list": {
                "1": {
                    "item_id": 1,
                    "demand": 264
                }
            },
            "seller": "C221",
            "start_time": 25200,
            "end_time": 75600
        },
        "98": {
            "id": 98,
            "code": "C260",
            "name": "WinMart+  Mỹ Đình",
            "location": {
                "lat": 21.028823,
                "long": 105.7752222
            },
            "demand_list": {
                "1": {
                    "item_id": 1,
                    "demand": 315
                }
            },
            "seller": "C423",
            "start_time": 27000,
            "end_time": 79200
        },
        "99": {
            "id": 99,
            "code": "C66",
            "name": "WinMart Lê Đức Thọ",
            "location": {
                "lat": 21.0283527,
                "long": 105.7688296
            },
            "demand_list": {
                "1": {
                    "item_id": 1,
                    "demand": 33
                }
            },
            "seller": "C53",
            "start_time": 27000,
            "end_time": 73800
        },
        "100": {
            "id": 100,
            "code": "C312",
            "name": "Circle K A8 Tôn Thất Tùng",
            "location": {
                "lat": 21.0043525,
                "long": 105.8311572
            },
            "demand_list": {
                "1": {
                    "item_id": 1,
                    "demand": 455
                }
            },
            "seller": "C273",
            "start_time": 25200,
            "end_time": 75600
        },
        "101": {
            "id": 101,
            "code": "C440",
            "name": "TH true mart Ngô Sĩ Liên Hà Nội",
            "location": {
                "lat": 21.026888,
                "long": 105.838622
            },
            "demand_list": {
                "1": {
                    "item_id": 1,
                    "demand": 186
                }
            },
            "seller": "C423",
            "start_time": 28800,
            "end_time": 79200
        },
        "102": {
            "id": 102,
            "code": "C311",
            "name": "Circle K D22, N12",
            "location": {
                "lat": 20.9877167,
                "long": 105.8315992
            },
            "demand_list": {
                "1": {
                    "item_id": 1,
                    "demand": 256
                }
            },
            "seller": "C259",
            "start_time": 25200,
            "end_time": 75600
        },
        "103": {
            "id": 103,
            "code": "C426",
            "name": "Cửa Hàng Nội Thất Đồ Gỗ Sunking",
            "location": {
                "lat": 20.9953007,
                "long": 105.8562083
            },
            "demand_list": {
                "1": {
                    "item_id": 1,
                    "demand": 407
                }
            },
            "seller": "C423",
            "start_time": 28800,
            "end_time": 79200
        },
        "104": {
            "id": 104,
            "code": "C420",
            "name": "Siêu thị Điện máy XANH - Khu Đầm Săn",
            "location": {
                "lat": 21.0553208,
                "long": 105.5798924
            },
            "demand_list": {
                "1": {
                    "item_id": 1,
                    "demand": 405
                }
            },
            "seller": "C273",
            "start_time": 28800,
            "end_time": 79200
        },
        "105": {
            "id": 105,
            "code": "C310",
            "name": "Circle K Hương Viên",
            "location": {
                "lat": 21.0129028,
                "long": 105.8562064
            },
            "demand_list": {
                "1": {
                    "item_id": 1,
                    "demand": 119
                }
            },
            "seller": "C423",
            "start_time": 25200,
            "end_time": 75600
        },
        "106": {
            "id": 106,
            "code": "C462",
            "name": "TH true mart Thanh Đàm Hà Nội",
            "location": {
                "lat": 20.9937332,
                "long": 105.888161
            },
            "demand_list": {
                "1": {
                    "item_id": 1,
                    "demand": 388
                }
            },
            "seller": "C5",
            "start_time": 28800,
            "end_time": 79200
        },
        "107": {
            "id": 107,
            "code": "C6",
            "name": "VinMart Đội Cấn",
            "location": {
                "lat": 21.0355053,
                "long": 105.8195195
            },
            "demand_list": {
                "1": {
                    "item_id": 1,
                    "demand": 47
                }
            },
            "seller": "C5",
            "start_time": 28800,
            "end_time": 75600
        },
        "108": {
            "id": 108,
            "code": "C249",
            "name": "WinMart+ 347 Bạch Mai",
            "location": {
                "lat": 21.0016986,
                "long": 105.8508168
            },
            "demand_list": {
                "1": {
                    "item_id": 1,
                    "demand": 128
                }
            },
            "seller": "C5",
            "start_time": 27000,
            "end_time": 79200
        },
        "109": {
            "id": 109,
            "code": "C103",
            "name": "WinMart+ - 284 Tựu Liệt, Tam Hiệp, Thanh Trì",
            "location": {
                "lat": 20.9530705,
                "long": 105.8338115
            },
            "demand_list": {
                "1": {
                    "item_id": 1,
                    "demand": 449
                }
            },
            "seller": "C273",
            "start_time": 27000,
            "end_time": 73800
        },
        "110": {
            "id": 110,
            "code": "C56",
            "name": "WinMart+ 80 Nguyễn Phúc Lai",
            "location": {
                "lat": 21.0198406,
                "long": 105.8213076
            },
            "demand_list": {
                "1": {
                    "item_id": 1,
                    "demand": 30
                }
            },
            "seller": "C461",
            "start_time": 27900,
            "end_time": 74700
        },
        "111": {
            "id": 111,
            "code": "C342",
            "name": "Circle k - N8A1 Nguyễn Thị Thập",
            "location": {
                "lat": 21.0045437,
                "long": 105.7996073
            },
            "demand_list": {
                "1": {
                    "item_id": 1,
                    "demand": 311
                }
            },
            "seller": "C273",
            "start_time": 25200,
            "end_time": 75600
        },
        "112": {
            "id": 112,
            "code": "C226",
            "name": "WinMart+ 86 Lạc Trung",
            "location": {
                "lat": 21.0031451,
                "long": 105.863833
            },
            "demand_list": {
                "1": {
                    "item_id": 1,
                    "demand": 278
                }
            },
            "seller": "C22",
            "start_time": 27000,
            "end_time": 79200
        },
        "113": {
            "id": 113,
            "code": "C188",
            "name": "WinMart+ 353 Nam Dư",
            "location": {
                "lat": 20.9792667,
                "long": 105.8864419
            },
            "demand_list": {
                "1": {
                    "item_id": 1,
                    "demand": 97
                }
            },
            "seller": "C53",
            "start_time": 28800,
            "end_time": 79200
        },
        "114": {
            "id": 114,
            "code": "C245",
            "name": "WinMart+ 242 Lê Thanh Nghị",
            "location": {
                "lat": 21.0019762,
                "long": 105.8424844
            },
            "demand_list": {
                "1": {
                    "item_id": 1,
                    "demand": 361
                }
            },
            "seller": "C143",
            "start_time": 27000,
            "end_time": 79200
        },
        "115": {
            "id": 115,
            "code": "C174",
            "name": "WinMart+ 86 Thanh Lân",
            "location": {
                "lat": 20.9899103,
                "long": 105.8884617
            },
            "demand_list": {
                "1": {
                    "item_id": 1,
                    "demand": 351
                }
            },
            "seller": "C143",
            "start_time": 28800,
            "end_time": 79200
        },
        "116": {
            "id": 116,
            "code": "C189",
            "name": "WinMart+ 68 Yên Duyên",
            "location": {
                "lat": 20.9724033,
                "long": 105.8681474
            },
            "demand_list": {
                "1": {
                    "item_id": 1,
                    "demand": 170
                }
            },
            "seller": "C221",
            "start_time": 28800,
            "end_time": 79200
        },
        "117": {
            "id": 117,
            "code": "C451",
            "name": "TH true mart Xuân La, Tây Hồ Hà Nội",
            "location": {
                "lat": 21.0615902,
                "long": 105.8082319
            },
            "demand_list": {
                "1": {
                    "item_id": 1,
                    "demand": 456
                }
            },
            "seller": "C259",
            "start_time": 28800,
            "end_time": 79200
        },
        "118": {
            "id": 118,
            "code": "C61",
            "name": "WinMart+ BNH SUỐI HOA - Bắc Ninh",
            "location": {
                "lat": 21.1895425,
                "long": 106.0763182
            },
            "demand_list": {
                "1": {
                    "item_id": 1,
                    "demand": 269
                }
            },
            "seller": "C259",
            "start_time": 27000,
            "end_time": 73800
        },
        "119": {
            "id": 119,
            "code": "C300",
            "name": "Circle K Giải Phóng",
            "location": {
                "lat": 20.991114,
                "long": 105.8407034
            },
            "demand_list": {
                "1": {
                    "item_id": 1,
                    "demand": 250
                }
            },
            "seller": "C5",
            "start_time": 25200,
            "end_time": 75600
        },
        "120": {
            "id": 120,
            "code": "C460",
            "name": "TH true mart Trần Đại Nghĩa Hà Nội",
            "location": {
                "lat": 21.0009951,
                "long": 105.8454309
            },
            "demand_list": {
                "1": {
                    "item_id": 1,
                    "demand": 210
                }
            },
            "seller": "C461",
            "start_time": 28800,
            "end_time": 79200
        },
        "121": {
            "id": 121,
            "code": "C20",
            "name": "VinMart+ 203 Nguyễn Văn Cừ - Bắc Ninh",
            "location": {
                "lat": 21.1732146,
                "long": 106.0534712
            },
            "demand_list": {
                "1": {
                    "item_id": 1,
                    "demand": 348
                }
            },
            "seller": "C221",
            "start_time": 28800,
            "end_time": 75600
        },
        "122": {
            "id": 122,
            "code": "C44",
            "name": "WinMart+28 Nguyễn Thái Học",
            "location": {
                "lat": 21.0292717,
                "long": 105.8405698
            },
            "demand_list": {
                "1": {
                    "item_id": 1,
                    "demand": 426
                }
            },
            "seller": "C22",
            "start_time": 27900,
            "end_time": 74700
        },
        "123": {
            "id": 123,
            "code": "C196",
            "name": "WinMart+ 142 Kim Giang",
            "location": {
                "lat": 20.9808756,
                "long": 105.8175831
            },
            "demand_list": {
                "1": {
                    "item_id": 1,
                    "demand": 232
                }
            },
            "seller": "C5",
            "start_time": 28800,
            "end_time": 79200
        },
        "124": {
            "id": 124,
            "code": "C412",
            "name": "Vua nệm -  142 P. Lò Đúc",
            "location": {
                "lat": 21.0125517,
                "long": 105.8583648
            },
            "demand_list": {
                "1": {
                    "item_id": 1,
                    "demand": 358
                }
            },
            "seller": "C221",
            "start_time": 30600,
            "end_time": 75600
        },
        "125": {
            "id": 125,
            "code": "C288",
            "name": "WinMart+ 54 Lý Thường Kiệt - Hà Đông",
            "location": {
                "lat": 20.9654288,
                "long": 105.7695437
            },
            "demand_list": {
                "1": {
                    "item_id": 1,
                    "demand": 439
                }
            },
            "seller": "C461",
            "start_time": 27000,
            "end_time": 79200
        },
        "126": {
            "id": 126,
            "code": "C77",
            "name": "WinMart Hà Đông",
            "location": {
                "lat": 20.9640178,
                "long": 105.7919202
            },
            "demand_list": {
                "1": {
                    "item_id": 1,
                    "demand": 171
                }
            },
            "seller": "C22",
            "start_time": 27000,
            "end_time": 73800
        },
        "127": {
            "id": 127,
            "code": "C153",
            "name": "WinMart+ 12 Phạm Tuấn Tài",
            "location": {
                "lat": 21.0417797,
                "long": 105.7869201
            },
            "demand_list": {
                "1": {
                    "item_id": 1,
                    "demand": 32
                }
            },
            "seller": "C273",
            "start_time": 28800,
            "end_time": 79200
        },
        "128": {
            "id": 128,
            "code": "C244",
            "name": "WinMart+ 35B Nguyễn Bỉnh Khiêm",
            "location": {
                "lat": 21.0159558,
                "long": 105.8486237
            },
            "demand_list": {
                "1": {
                    "item_id": 1,
                    "demand": 150
                }
            },
            "seller": "C423",
            "start_time": 27000,
            "end_time": 79200
        },
        "129": {
            "id": 129,
            "code": "C148",
            "name": "WinMart+ Ngõ 76 Mai Dịch",
            "location": {
                "lat": 21.0412539,
                "long": 105.7750866
            },
            "demand_list": {
                "1": {
                    "item_id": 1,
                    "demand": 53
                }
            },
            "seller": "C143",
            "start_time": 28800,
            "end_time": 79200
        },
        "130": {
            "id": 130,
            "code": "C358",
            "name": "Điện máy xanh - 194 Phạm Văn Đồng",
            "location": {
                "lat": 21.0465783,
                "long": 105.7809096
            },
            "demand_list": {
                "1": {
                    "item_id": 1,
                    "demand": 272
                }
            },
            "seller": "C221",
            "start_time": 28800,
            "end_time": 79200
        },
        "131": {
            "id": 131,
            "code": "C82",
            "name": "WinMart Thụy Khuê",
            "location": {
                "lat": 21.0404572,
                "long": 105.8264387
            },
            "demand_list": {
                "1": {
                    "item_id": 1,
                    "demand": 81
                }
            },
            "seller": "C273",
            "start_time": 27000,
            "end_time": 73800
        },
        "132": {
            "id": 132,
            "code": "C454",
            "name": "TH true mart Vũ Trọng Phụng Hà Nội",
            "location": {
                "lat": 21.0002111,
                "long": 105.8078217
            },
            "demand_list": {
                "1": {
                    "item_id": 1,
                    "demand": 400
                }
            },
            "seller": "C116",
            "start_time": 28800,
            "end_time": 79200
        },
        "133": {
            "id": 133,
            "code": "C167",
            "name": "WinMart+ Trần Điền",
            "location": {
                "lat": 20.9914504,
                "long": 105.8325043
            },
            "demand_list": {
                "1": {
                    "item_id": 1,
                    "demand": 475
                }
            },
            "seller": "C22",
            "start_time": 28800,
            "end_time": 79200
        },
        "134": {
            "id": 134,
            "code": "C213",
            "name": "WinMart+ 22 Thạch Bàn",
            "location": {
                "lat": 21.0271937,
                "long": 105.9109711
            },
            "demand_list": {
                "1": {
                    "item_id": 1,
                    "demand": 485
                }
            },
            "seller": "C461",
            "start_time": 27000,
            "end_time": 79200
        },
        "135": {
            "id": 135,
            "code": "C237",
            "name": "WinMart+ 69 Hồng Mai",
            "location": {
                "lat": 20.998553,
                "long": 105.852251
            },
            "demand_list": {
                "1": {
                    "item_id": 1,
                    "demand": 45
                }
            },
            "seller": "C461",
            "start_time": 27000,
            "end_time": 79200
        },
        "136": {
            "id": 136,
            "code": "C104",
            "name": "WinMart+ Phố Nỉ, Sóc Sơn",
            "location": {
                "lat": 21.3111262,
                "long": 105.8694258
            },
            "demand_list": {
                "1": {
                    "item_id": 1,
                    "demand": 308
                }
            },
            "seller": "C53",
            "start_time": 27000,
            "end_time": 73800
        },
        "137": {
            "id": 137,
            "code": "C241",
            "name": "WinMart+ 317 Phố Vọng",
            "location": {
                "lat": 20.9940593,
                "long": 105.842199
            },
            "demand_list": {
                "1": {
                    "item_id": 1,
                    "demand": 150
                }
            },
            "seller": "C221",
            "start_time": 27000,
            "end_time": 79200
        },
        "138": {
            "id": 138,
            "code": "C464",
            "name": "TH true mart Thạch Bàn Hà Nội",
            "location": {
                "lat": 21.0260984,
                "long": 105.9096785
            },
            "demand_list": {
                "1": {
                    "item_id": 1,
                    "demand": 47
                }
            },
            "seller": "C53",
            "start_time": 28800,
            "end_time": 79200
        },
        "139": {
            "id": 139,
            "code": "C75",
            "name": "WinMart Bắc Từ Liêm",
            "location": {
                "lat": 21.0530292,
                "long": 105.7800956
            },
            "demand_list": {
                "1": {
                    "item_id": 1,
                    "demand": 74
                }
            },
            "seller": "C53",
            "start_time": 27000,
            "end_time": 73800
        },
        "140": {
            "id": 140,
            "code": "C295",
            "name": "Circle K Kim Ngưu",
            "location": {
                "lat": 20.9990116,
                "long": 105.861635
            },
            "demand_list": {
                "1": {
                    "item_id": 1,
                    "demand": 189
                }
            },
            "seller": "C423",
            "start_time": 25200,
            "end_time": 75600
        },
        "141": {
            "id": 141,
            "code": "C80",
            "name": "WinMart Times City",
            "location": {
                "lat": 20.9939208,
                "long": 105.8695352
            },
            "demand_list": {
                "1": {
                    "item_id": 1,
                    "demand": 426
                }
            },
            "seller": "C259",
            "start_time": 27000,
            "end_time": 73800
        },
        "142": {
            "id": 142,
            "code": "C123",
            "name": "WinMart+ 66 Đặng Tiến Đông",
            "location": {
                "lat": 21.0159499,
                "long": 105.8197992
            },
            "demand_list": {
                "1": {
                    "item_id": 1,
                    "demand": 269
                }
            },
            "seller": "C221",
            "start_time": 27000,
            "end_time": 73800
        },
        "143": {
            "id": 143,
            "code": "C215",
            "name": "WinMart+ 38 Trường Lâm",
            "location": {
                "lat": 21.0620238,
                "long": 105.8962722
            },
            "demand_list": {
                "1": {
                    "item_id": 1,
                    "demand": 73
                }
            },
            "seller": "C273",
            "start_time": 27000,
            "end_time": 79200
        },
        "144": {
            "id": 144,
            "code": "C277",
            "name": "WinMart+ 272 Thụy Phương",
            "location": {
                "lat": 21.0927482,
                "long": 105.7777914
            },
            "demand_list": {
                "1": {
                    "item_id": 1,
                    "demand": 111
                }
            },
            "seller": "C53",
            "start_time": 27000,
            "end_time": 79200
        },
        "145": {
            "id": 145,
            "code": "C262",
            "name": "WinMart+ 156 Trần Bình",
            "location": {
                "lat": 21.030459,
                "long": 105.7758655
            },
            "demand_list": {
                "1": {
                    "item_id": 1,
                    "demand": 369
                }
            },
            "seller": "C423",
            "start_time": 27000,
            "end_time": 79200
        },
        "146": {
            "id": 146,
            "code": "C27",
            "name": "WinMart+ Bát Tràng",
            "location": {
                "lat": 20.9788994,
                "long": 105.9160607
            },
            "demand_list": {
                "1": {
                    "item_id": 1,
                    "demand": 267
                }
            },
            "seller": "C423",
            "start_time": 28800,
            "end_time": 75600
        },
        "147": {
            "id": 147,
            "code": "C218",
            "name": "WinMart+ 27 Ngô Thì Nhậm",
            "location": {
                "lat": 21.0167733,
                "long": 105.8543229
            },
            "demand_list": {
                "1": {
                    "item_id": 1,
                    "demand": 260
                }
            },
            "seller": "C143",
            "start_time": 27000,
            "end_time": 79200
        },
        "148": {
            "id": 148,
            "code": "C81",
            "name": "WinMart Trung Hòa",
            "location": {
                "lat": 21.0070457,
                "long": 105.8029953
            },
            "demand_list": {
                "1": {
                    "item_id": 1,
                    "demand": 121
                }
            },
            "seller": "C259",
            "start_time": 27000,
            "end_time": 73800
        },
        "149": {
            "id": 149,
            "code": "C201",
            "name": "WinMart+ 1D Ngõ 405 Ngọc Thụy",
            "location": {
                "lat": 21.0621545,
                "long": 105.8614703
            },
            "demand_list": {
                "1": {
                    "item_id": 1,
                    "demand": 123
                }
            },
            "seller": "C423",
            "start_time": 27000,
            "end_time": 79200
        },
        "150": {
            "id": 150,
            "code": "C204",
            "name": "WinMart+ 166 Ái Mộ",
            "location": {
                "lat": 21.0387217,
                "long": 105.8707883
            },
            "demand_list": {
                "1": {
                    "item_id": 1,
                    "demand": 231
                }
            },
            "seller": "C273",
            "start_time": 27000,
            "end_time": 79200
        },
        "151": {
            "id": 151,
            "code": "C154",
            "name": "WinMart+ Chelsea Park, Trung Kính",
            "location": {
                "lat": 21.0186652,
                "long": 105.7932229
            },
            "demand_list": {
                "1": {
                    "item_id": 1,
                    "demand": 237
                }
            },
            "seller": "C461",
            "start_time": 28800,
            "end_time": 79200
        },
        "152": {
            "id": 152,
            "code": "C303",
            "name": "Circle K 144 Hồng Mai",
            "location": {
                "lat": 20.9988981,
                "long": 105.8530086
            },
            "demand_list": {
                "1": {
                    "item_id": 1,
                    "demand": 379
                }
            },
            "seller": "C259",
            "start_time": 25200,
            "end_time": 75600
        },
        "153": {
            "id": 153,
            "code": "C197",
            "name": "WinMart+ 100 Nguyễn Sơn",
            "location": {
                "lat": 21.0473163,
                "long": 105.8770613
            },
            "demand_list": {
                "1": {
                    "item_id": 1,
                    "demand": 92
                }
            },
            "seller": "C143",
            "start_time": 28800,
            "end_time": 79200
        },
        "154": {
            "id": 154,
            "code": "C466",
            "name": "TH true mart Tân Mai Hà Nội",
            "location": {
                "lat": 20.983445,
                "long": 105.8510431
            },
            "demand_list": {
                "1": {
                    "item_id": 1,
                    "demand": 440
                }
            },
            "seller": "C221",
            "start_time": 28800,
            "end_time": 79200
        },
        "155": {
            "id": 155,
            "code": "C149",
            "name": "WinMart+ Ngõ 76 Mai Dịch",
            "location": {
                "lat": 21.0415329,
                "long": 105.794327
            },
            "demand_list": {
                "1": {
                    "item_id": 1,
                    "demand": 266
                }
            },
            "seller": "C53",
            "start_time": 28800,
            "end_time": 79200
        },
        "156": {
            "id": 156,
            "code": "C452",
            "name": "TH true mart Trương Định Hà Nội",
            "location": {
                "lat": 20.9813346,
                "long": 105.8454582
            },
            "demand_list": {
                "1": {
                    "item_id": 1,
                    "demand": 330
                }
            },
            "seller": "C116",
            "start_time": 28800,
            "end_time": 79200
        },
        "157": {
            "id": 157,
            "code": "C152",
            "name": "WinMart+ 121B Quan Hoa",
            "location": {
                "lat": 21.0342858,
                "long": 105.8040881
            },
            "demand_list": {
                "1": {
                    "item_id": 1,
                    "demand": 294
                }
            },
            "seller": "C53",
            "start_time": 28800,
            "end_time": 79200
        },
        "158": {
            "id": 158,
            "code": "C253",
            "name": "WinMart+ - Chung cư 46 Lạc Trung",
            "location": {
                "lat": 21.0038282,
                "long": 105.8661158
            },
            "demand_list": {
                "1": {
                    "item_id": 1,
                    "demand": 445
                }
            },
            "seller": "C143",
            "start_time": 27000,
            "end_time": 79200
        },
        "159": {
            "id": 159,
            "code": "C140",
            "name": "WinMart+ 639 Vũ Tông Phan",
            "location": {
                "lat": 20.98258,
                "long": 105.8167033
            },
            "demand_list": {
                "1": {
                    "item_id": 1,
                    "demand": 462
                }
            },
            "seller": "C143",
            "start_time": 28800,
            "end_time": 79200
        },
        "160": {
            "id": 160,
            "code": "C233",
            "name": "WinMart+ 49B Ngõ 651 Minh Khai",
            "location": {
                "lat": 21.0034068,
                "long": 105.8682953
            },
            "demand_list": {
                "1": {
                    "item_id": 1,
                    "demand": 289
                }
            },
            "seller": "C259",
            "start_time": 27000,
            "end_time": 79200
        },
        "161": {
            "id": 161,
            "code": "C329",
            "name": "Circle K - 6 Ngõ 124 Phố Vĩnh Tuy",
            "location": {
                "lat": 21.0010312,
                "long": 105.8754738
            },
            "demand_list": {
                "1": {
                    "item_id": 1,
                    "demand": 366
                }
            },
            "seller": "C143",
            "start_time": 25200,
            "end_time": 75600
        },
        "162": {
            "id": 162,
            "code": "C128",
            "name": "WinMart+ 150 Nguyễn Lương Bằng",
            "location": {
                "lat": 21.0156452,
                "long": 105.8280662
            },
            "demand_list": {
                "1": {
                    "item_id": 1,
                    "demand": 378
                }
            },
            "seller": "C5",
            "start_time": 28800,
            "end_time": 79200
        },
        "163": {
            "id": 163,
            "code": "C367",
            "name": "Điện Máy Xanh Thái Hà",
            "location": {
                "lat": 21.0141822,
                "long": 105.818148
            },
            "demand_list": {
                "1": {
                    "item_id": 1,
                    "demand": 389
                }
            },
            "seller": "C221",
            "start_time": 28800,
            "end_time": 79200
        },
        "164": {
            "id": 164,
            "code": "C276",
            "name": "WinMart+ 271 Nguyễn Hoàng Tôn",
            "location": {
                "lat": 21.0727818,
                "long": 105.8024247
            },
            "demand_list": {
                "1": {
                    "item_id": 1,
                    "demand": 147
                }
            },
            "seller": "C116",
            "start_time": 27000,
            "end_time": 79200
        },
        "165": {
            "id": 165,
            "code": "C242",
            "name": "WinMart+ 66 Đại Cổ Việt",
            "location": {
                "lat": 21.0084179,
                "long": 105.8474426
            },
            "demand_list": {
                "1": {
                    "item_id": 1,
                    "demand": 24
                }
            },
            "seller": "C143",
            "start_time": 27000,
            "end_time": 79200
        },
        "166": {
            "id": 166,
            "code": "C195",
            "name": "WinMart+ 91 Vĩnh Hưng",
            "location": {
                "lat": 20.9859011,
                "long": 105.8760171
            },
            "demand_list": {
                "1": {
                    "item_id": 1,
                    "demand": 54
                }
            },
            "seller": "C116",
            "start_time": 28800,
            "end_time": 79200
        },
        "167": {
            "id": 167,
            "code": "C124",
            "name": "WinMart+ 158 Thái Thịnh",
            "location": {
                "lat": 21.012307,
                "long": 105.816945
            },
            "demand_list": {
                "1": {
                    "item_id": 1,
                    "demand": 134
                }
            },
            "seller": "C273",
            "start_time": 28800,
            "end_time": 79200
        },
        "168": {
            "id": 168,
            "code": "C376",
            "name": "Siêu thị Điện máy XANH  - 194 Đường Vạn Phúc",
            "location": {
                "lat": 20.9831231,
                "long": 105.7701552
            },
            "demand_list": {
                "1": {
                    "item_id": 1,
                    "demand": 71
                }
            },
            "seller": "C53",
            "start_time": 28800,
            "end_time": 79200
        },
        "169": {
            "id": 169,
            "code": "C38",
            "name": "WinMart+ 50 Nguyễn Hoàng Tôn",
            "location": {
                "lat": 21.0715449,
                "long": 105.8064137
            },
            "demand_list": {
                "1": {
                    "item_id": 1,
                    "demand": 326
                }
            },
            "seller": "C461",
            "start_time": 27000,
            "end_time": 73800
        },
        "170": {
            "id": 170,
            "code": "C37",
            "name": "WinMart+ 47 Phó Đức Chính",
            "location": {
                "lat": 21.048936,
                "long": 105.841036
            },
            "demand_list": {
                "1": {
                    "item_id": 1,
                    "demand": 488
                }
            },
            "seller": "C221",
            "start_time": 27000,
            "end_time": 73800
        },
        "171": {
            "id": 171,
            "code": "C340",
            "name": "Circle k - 7 Nguyễn Thị Định",
            "location": {
                "lat": 21.0127125,
                "long": 105.8036719
            },
            "demand_list": {
                "1": {
                    "item_id": 1,
                    "demand": 307
                }
            },
            "seller": "C53",
            "start_time": 25200,
            "end_time": 75600
        },
        "172": {
            "id": 172,
            "code": "C356",
            "name": "Circle K - Số 177 Xuân Thủy",
            "location": {
                "lat": 21.0364029,
                "long": 105.7837198
            },
            "demand_list": {
                "1": {
                    "item_id": 1,
                    "demand": 457
                }
            },
            "seller": "C221",
            "start_time": 25200,
            "end_time": 75600
        },
        "173": {
            "id": 173,
            "code": "C137",
            "name": "WinMart+ 208 Khương Trung",
            "location": {
                "lat": 20.99025,
                "long": 105.817569
            },
            "demand_list": {
                "1": {
                    "item_id": 1,
                    "demand": 184
                }
            },
            "seller": "C53",
            "start_time": 28800,
            "end_time": 79200
        },
        "174": {
            "id": 174,
            "code": "C47",
            "name": "WinMart+ 31 Tân Ấp",
            "location": {
                "lat": 21.0460677,
                "long": 105.8462736
            },
            "demand_list": {
                "1": {
                    "item_id": 1,
                    "demand": 434
                }
            },
            "seller": "C143",
            "start_time": 27900,
            "end_time": 74700
        },
        "175": {
            "id": 175,
            "code": "C350",
            "name": "Circle K - 218 Nguyễn Huy Tưởng",
            "location": {
                "lat": 20.996892,
                "long": 105.803578
            },
            "demand_list": {
                "1": {
                    "item_id": 1,
                    "demand": 480
                }
            },
            "seller": "C221",
            "start_time": 25200,
            "end_time": 75600
        },
        "176": {
            "id": 176,
            "code": "C63",
            "name": "WinMart Royal City",
            "location": {
                "lat": 21.0037001,
                "long": 105.816549
            },
            "demand_list": {
                "1": {
                    "item_id": 1,
                    "demand": 233
                }
            },
            "seller": "C143",
            "start_time": 27000,
            "end_time": 73800
        },
        "177": {
            "id": 177,
            "code": "C136",
            "name": "WinMart+ 46 Hạ Đình",
            "location": {
                "lat": 21.0101073,
                "long": 105.8045239
            },
            "demand_list": {
                "1": {
                    "item_id": 1,
                    "demand": 456
                }
            },
            "seller": "C461",
            "start_time": 28800,
            "end_time": 79200
        },
        "178": {
            "id": 178,
            "code": "C163",
            "name": "WinMart+ Hoàng Văn Thái - Khương Mai",
            "location": {
                "lat": 20.9903456,
                "long": 105.8335762
            },
            "demand_list": {
                "1": {
                    "item_id": 1,
                    "demand": 331
                }
            },
            "seller": "C143",
            "start_time": 28800,
            "end_time": 79200
        },
        "179": {
            "id": 179,
            "code": "C13",
            "name": "VinMart Bà Triệu",
            "location": {
                "lat": 21.0111389,
                "long": 105.8494609
            },
            "demand_list": {
                "1": {
                    "item_id": 1,
                    "demand": 342
                }
            },
            "seller": "C143",
            "start_time": 28800,
            "end_time": 75600
        },
        "180": {
            "id": 180,
            "code": "C2",
            "name": "VinMart Đại La",
            "location": {
                "lat": 20.9964605,
                "long": 105.8446364
            },
            "demand_list": {
                "1": {
                    "item_id": 1,
                    "demand": 254
                }
            },
            "seller": "C5",
            "start_time": 28800,
            "end_time": 75600
        },
        "181": {
            "id": 181,
            "code": "C21",
            "name": "VinMart+ 73 Phố Vũ - Bắc Ninh",
            "location": {
                "lat": 21.1757102,
                "long": 106.0776232
            },
            "demand_list": {
                "1": {
                    "item_id": 1,
                    "demand": 3
                }
            },
            "seller": "C259",
            "start_time": 28800,
            "end_time": 75600
        },
        "182": {
            "id": 182,
            "code": "C344",
            "name": "Circle k - 5 Nguyễn Quý Đức",
            "location": {
                "lat": 20.9913234,
                "long": 105.799553
            },
            "demand_list": {
                "1": {
                    "item_id": 1,
                    "demand": 268
                }
            },
            "seller": "C22",
            "start_time": 25200,
            "end_time": 75600
        },
        "183": {
            "id": 183,
            "code": "C338",
            "name": "Circle K Hàng Điếu",
            "location": {
                "lat": 21.0319939,
                "long": 105.8468804
            },
            "demand_list": {
                "1": {
                    "item_id": 1,
                    "demand": 314
                }
            },
            "seller": "C22",
            "start_time": 25200,
            "end_time": 75600
        },
        "184": {
            "id": 184,
            "code": "C267",
            "name": "WinMart+ 5 Nhật Tảo",
            "location": {
                "lat": 21.087577,
                "long": 105.7868327
            },
            "demand_list": {
                "1": {
                    "item_id": 1,
                    "demand": 219
                }
            },
            "seller": "C53",
            "start_time": 27000,
            "end_time": 79200
        },
        "185": {
            "id": 185,
            "code": "C65",
            "name": "WinMart Lý Thái Tổ",
            "location": {
                "lat": 21.0294597,
                "long": 105.8554743
            },
            "demand_list": {
                "1": {
                    "item_id": 1,
                    "demand": 400
                }
            },
            "seller": "C22",
            "start_time": 27000,
            "end_time": 73800
        },
        "186": {
            "id": 186,
            "code": "C217",
            "name": "WinMart+ 24 Sài Đồng",
            "location": {
                "lat": 21.0332449,
                "long": 105.9095876
            },
            "demand_list": {
                "1": {
                    "item_id": 1,
                    "demand": 307
                }
            },
            "seller": "C22",
            "start_time": 27000,
            "end_time": 79200
        },
        "187": {
            "id": 187,
            "code": "C120",
            "name": "WinMart+ 612A Lạc Long Quân",
            "location": {
                "lat": 21.067045,
                "long": 105.810878
            },
            "demand_list": {
                "1": {
                    "item_id": 1,
                    "demand": 350
                }
            },
            "seller": "C143",
            "start_time": 27000,
            "end_time": 73800
        },
        "188": {
            "id": 188,
            "code": "C32",
            "name": "WinMart+ 123 Âu Cơ",
            "location": {
                "lat": 21.0635658,
                "long": 105.8314034
            },
            "demand_list": {
                "1": {
                    "item_id": 1,
                    "demand": 493
                }
            },
            "seller": "C5",
            "start_time": 27000,
            "end_time": 73800
        },
        "189": {
            "id": 189,
            "code": "C365",
            "name": "Điện máy xanh - 421 Đường Phạm Văn Đồng",
            "location": {
                "lat": 21.0605827,
                "long": 105.7836325
            },
            "demand_list": {
                "1": {
                    "item_id": 1,
                    "demand": 34
                }
            },
            "seller": "C259",
            "start_time": 28800,
            "end_time": 79200
        },
        "190": {
            "id": 190,
            "code": "C39",
            "name": "WinMart+ 18B Nguyễn Biểu",
            "location": {
                "lat": 21.0415902,
                "long": 105.8399122
            },
            "demand_list": {
                "1": {
                    "item_id": 1,
                    "demand": 408
                }
            },
            "seller": "C5",
            "start_time": 27000,
            "end_time": 73800
        },
        "191": {
            "id": 191,
            "code": "C254",
            "name": "WinMart+ Tu Hoàng - Phương Canh",
            "location": {
                "lat": 21.0519932,
                "long": 105.7306692
            },
            "demand_list": {
                "1": {
                    "item_id": 1,
                    "demand": 321
                }
            },
            "seller": "C116",
            "start_time": 27000,
            "end_time": 79200
        },
        "192": {
            "id": 192,
            "code": "C52",
            "name": "WinMart+ 26B Hòe Nhai",
            "location": {
                "lat": 21.0412286,
                "long": 105.8462804
            },
            "demand_list": {
                "1": {
                    "item_id": 1,
                    "demand": 176
                }
            },
            "seller": "C143",
            "start_time": 27900,
            "end_time": 74700
        },
        "193": {
            "id": 193,
            "code": "C448",
            "name": "TH true mart Doãn Kế Thiện Hà Nội",
            "location": {
                "lat": 21.0419265,
                "long": 105.775327
            },
            "demand_list": {
                "1": {
                    "item_id": 1,
                    "demand": 148
                }
            },
            "seller": "C461",
            "start_time": 28800,
            "end_time": 79200
        },
        "194": {
            "id": 194,
            "code": "C341",
            "name": "Circle k - 125 Hoàng Ngân",
            "location": {
                "lat": 21.0089987,
                "long": 105.8065561
            },
            "demand_list": {
                "1": {
                    "item_id": 1,
                    "demand": 46
                }
            },
            "seller": "C273",
            "start_time": 25200,
            "end_time": 75600
        },
        "195": {
            "id": 195,
            "code": "C238",
            "name": "WinMart+ 145 Lò Đúc",
            "location": {
                "lat": 21.009874,
                "long": 105.8605751
            },
            "demand_list": {
                "1": {
                    "item_id": 1,
                    "demand": 43
                }
            },
            "seller": "C423",
            "start_time": 27000,
            "end_time": 79200
        },
        "196": {
            "id": 196,
            "code": "C463",
            "name": "TH true mart Thành Công Hà Nội",
            "location": {
                "lat": 21.0227067,
                "long": 105.8161176
            },
            "demand_list": {
                "1": {
                    "item_id": 1,
                    "demand": 495
                }
            },
            "seller": "C461",
            "start_time": 28800,
            "end_time": 79200
        },
        "197": {
            "id": 197,
            "code": "C108",
            "name": "WinMart+ 78 Quốc lộ 3 Phủ Lỗ",
            "location": {
                "lat": 21.205374,
                "long": 105.8487279
            },
            "demand_list": {
                "1": {
                    "item_id": 1,
                    "demand": 32
                }
            },
            "seller": "C143",
            "start_time": 27000,
            "end_time": 73800
        },
        "198": {
            "id": 198,
            "code": "C354",
            "name": "Circle K - 97 Văn Cao",
            "location": {
                "lat": 21.0393145,
                "long": 105.8159654
            },
            "demand_list": {
                "1": {
                    "item_id": 1,
                    "demand": 327
                }
            },
            "seller": "C143",
            "start_time": 25200,
            "end_time": 75600
        },
        "199": {
            "id": 199,
            "code": "C335",
            "name": "Circle K - Rice City Linh Đàm",
            "location": {
                "lat": 20.9633858,
                "long": 105.8230591
            },
            "demand_list": {
                "1": {
                    "item_id": 1,
                    "demand": 63
                }
            },
            "seller": "C53",
            "start_time": 25200,
            "end_time": 75600
        }
    }
}